predikon/__init__.py
predikon/models.py
predikon-0.4.dist-info/LICENSE.txt
predikon-0.4.dist-info/METADATA
predikon-0.4.dist-info/WHEEL
predikon-0.4.dist-info/top_level.txt
predikon-0.4.dist-info/RECORD
