Metadata-Version: 2.1
Name: predikon
Version: 0.4
Summary: Predikon: Sub-Matrix Factorization for Real-Time Vote Prediction
Home-page: https://github.com/indy-lab/predikon-lib
Author: A. Immer, V. Kristof
License: MIT
Platform: UNKNOWN
Requires-Python: >=3.5
Requires-Dist: numpy (>=1.0.0)
Requires-Dist: scikit-learn (>=0.16.1)
